kcp/__init__.py
kcp/client.py
kcp/exceptions.py
kcp/extension.cp38-win_amd64.pyd
kcp/extension.pyi
kcp/extension.pyx
kcp/ikcp.c
kcp/ikcp.h
kcp/py.typed
kcp/server.py
kcp-0.1.6.dist-info/LICENSE
kcp-0.1.6.dist-info/METADATA
kcp-0.1.6.dist-info/WHEEL
kcp-0.1.6.dist-info/RECORD
