Metadata-Version: 2.1
Name: kcp
Version: 0.1.6
Summary: Python bindings and networking for the KCP protocol.
Home-page: https://github.com/RealistikDash/kcp.py
License: MIT
Keywords: kcp,server,client,async,asyncio
Author: RealistikDash
Requires-Python: >=3.7
Classifier: Development Status :: 4 - Beta
Classifier: Intended Audience :: Developers
Classifier: License :: OSI Approved :: MIT License
Classifier: Operating System :: OS Independent
Classifier: Programming Language :: Python :: 3
Classifier: Programming Language :: Python :: 3.7
Classifier: Programming Language :: Python :: 3.8
Classifier: Programming Language :: Python :: 3.9
Classifier: Programming Language :: Python :: 3.10
Classifier: Programming Language :: Python :: 3.11
Classifier: Programming Language :: Python :: 3.12
Classifier: Programming Language :: Python :: 3.13
Classifier: Topic :: Utilities
Classifier: Typing :: Typed
Project-URL: Documentation, https://github.com/RealistikDash/kcp.py
Project-URL: Issues, https://github.com/RealistikDash/kcp.py/issues
Project-URL: Repository, https://github.com/RealistikDash/kcp.py
